xslide/__init__.py
xslide/serve_slides.py
xslide/xslide.css
xslide-0.1.2.dist-info/DESCRIPTION.rst
xslide-0.1.2.dist-info/METADATA
xslide-0.1.2.dist-info/RECORD
xslide-0.1.2.dist-info/WHEEL
xslide-0.1.2.dist-info/entry_points.txt
xslide-0.1.2.dist-info/metadata.json
xslide-0.1.2.dist-info/top_level.txt
