Metadata-Version: 2.0
Name: xslide
Version: 0.1.2
Summary: Helper for creating presentation slides for developers. Markdown + graphs + html = big fun.
Home-page: https://gitlab.com/kamichal/XSLIDE
Author: Michał Kaczmarczyk
Author-email: michal.s.kaczmarczyk@gmail.com
Maintainer: Michał Kaczmarczyk
Maintainer-email: michal.s.kaczmarczyk@gmail.com
License: MIT license
Platform: UNKNOWN
Classifier: Development Status :: 4 - Beta
Classifier: License :: OSI Approved :: MIT License
Classifier: Operating System :: OS Independent
Classifier: Programming Language :: Python
Classifier: Programming Language :: Python :: 3.5
Classifier: Programming Language :: Python :: 3.6
Classifier: Programming Language :: Python :: 3.7
Classifier: Topic :: Multimedia :: Graphics :: Presentation
Requires-Dist: grot (<0.2.0,>=0.1.1)
Requires-Dist: livereload (<2.7.0,>=2.6.0)
Requires-Dist: markdown (<3.1.0,>=3.0.1)
Requires-Dist: xplant (<0.4.0,>=0.3.2)
